ticsummary/__init__.py
ticsummary/__main__.py
ticsummary/tempCodeRunnerFile.py
neofti_ticsummary-1.2.23.dist-info/METADATA
neofti_ticsummary-1.2.23.dist-info/WHEEL
neofti_ticsummary-1.2.23.dist-info/entry_points.txt
neofti_ticsummary-1.2.23.dist-info/top_level.txt
neofti_ticsummary-1.2.23.dist-info/RECORD
