Metadata-Version: 2.1
Name: neofti_ticsummary
Version: 1.2.23
Summary: TIC data viewer starter
Home-page: 
Author: DmitryKorovkin
Author-email: d.korovkin69@gmail.com
Classifier: Programming Language :: Python :: 3
Classifier: License :: OSI Approved :: MIT License
Classifier: Operating System :: OS Independent
Requires-Dist: neofti-ticsummary-domain
Requires-Dist: requests
Requires-Dist: pyqt6
